<?xml version="1.0" encoding="UTF-8"?>
<objects serializationModel="Studio.02.01.00">
	<object class="AudioFile" id="{5f8022fd-38e8-478c-a64c-5a1f361b346c}">
		<property name="assetPath">
			<value>MusicLayers/Game stems Dillan 01-06/Game 5-Reaktor 6.wav</value>
		</property>
		<property name="isStreaming">
			<value>true</value>
		</property>
		<property name="frequencyInKHz">
			<value>44.0999985</value>
		</property>
		<property name="channelCount">
			<value>2</value>
		</property>
		<property name="length">
			<value>74</value>
		</property>
		<relationship name="masterAssetFolder">
			<destination>{2aa189aa-2b15-4400-8911-0bc3e274fc7a}</destination>
		</relationship>
	</object>
</objects>
